fetchas/__init__.py
fetchas/command_line.py
fetchas/user_agents.py
fetchas-0.2.dist-info/METADATA
fetchas-0.2.dist-info/WHEEL
fetchas-0.2.dist-info/entry_points.txt
fetchas-0.2.dist-info/top_level.txt
fetchas-0.2.dist-info/RECORD
