Metadata-Version: 2.1
Name: fetchas
Version: 0.2
Summary: Fetch web pages as robot
Home-page: https://github.com/rosenhagen/fetchas
Author: Henning Rosenhagen
Author-email: hcodenhagen@gmail.com
License: UNKNOWN
Platform: UNKNOWN
Classifier: License :: OSI Approved :: MIT License
Classifier: Programming Language :: Python :: 3
Classifier: Programming Language :: Python :: 3.7
Requires-Python: >=3
Requires-Dist: requests
